ipicn/__init__.py
ipicn/constants.py
ipicn/updater.py
ipicn-2021.5.5.dist-info/LICENSE
ipicn-2021.5.5.dist-info/WHEEL
ipicn-2021.5.5.dist-info/METADATA
ipicn-2021.5.5.dist-info/RECORD
