Metadata-Version: 2.1
Name: ipicn
Version: 2021.5.5
Summary: A tool to help determine whether ip is in China
Author: ehco1996
Author-email: zh19960202@gmail.com
Requires-Python: >=3.7,<4.0
Classifier: Programming Language :: Python :: 3
Classifier: Programming Language :: Python :: 3.7
Classifier: Programming Language :: Python :: 3.8
Classifier: Programming Language :: Python :: 3.9
Requires-Dist: geoip2 (>=4.1.0,<5.0.0)
Requires-Dist: ipaddress (>=1.0.23,<2.0.0)
Requires-Dist: requests (>=2.25.1,<3.0.0)
